cliep/__init__.py
cliep/args.py
cliep/util.py
cliep-1.0.3.dist-info/LICENSE
cliep-1.0.3.dist-info/METADATA
cliep-1.0.3.dist-info/WHEEL
cliep-1.0.3.dist-info/top_level.txt
cliep-1.0.3.dist-info/RECORD
