Metadata-Version: 2.1
Name: cliep
Version: 1.0.3
Summary: Simple CLI entrypoint and argument parsing.
Home-page: https://github.com/hsorenson/cliep
Author: Harald Sorenson
Author-email: haraldesorenson@gmail.com
License: UNKNOWN
Platform: UNKNOWN
Classifier: Programming Language :: Python :: 3
Classifier: License :: OSI Approved :: GNU General Public License v3 or later (GPLv3+)
Classifier: Operating System :: OS Independent
